{
  "afk-fresh": {
    "ticks": 378,
    "wavesCleared": 0,
    "kills": 0,
    "outcome": "defeat",
    "sparks": 0,
    "stateHash": "2b242e06"
  },
  "greedy-fresh": {
    "ticks": 2227,
    "wavesCleared": 4,
    "kills": 122,
    "outcome": "defeat",
    "sparks": 70,
    "stateHash": "e7005ebb"
  },
  "balanced-fresh": {
    "ticks": 7991,
    "wavesCleared": 13,
    "kills": 828,
    "outcome": "defeat",
    "sparks": 264,
    "stateHash": "e55dd301"
  },
  "balanced-rich": {
    "ticks": 7741,
    "wavesCleared": 13,
    "kills": 774,
    "outcome": "defeat",
    "sparks": 259,
    "stateHash": "e6a112b6"
  }
}
